molsol/KDESol.py
molsol/__init__.py
molsol/version.py
molsol/voc.json
molsol/kde10_lstm_r/m0.h5
molsol/kde10_lstm_r/m0.json
molsol/kde10_lstm_r/m1.h5
molsol/kde10_lstm_r/m1.json
molsol/kde10_lstm_r/m2.h5
molsol/kde10_lstm_r/m2.json
molsol/kde10_lstm_r/m3.h5
molsol/kde10_lstm_r/m3.json
molsol/kde10_lstm_r/m4.h5
molsol/kde10_lstm_r/m4.json
molsol/kde10_lstm_r/m5.h5
molsol/kde10_lstm_r/m5.json
molsol/kde10_lstm_r/m6.h5
molsol/kde10_lstm_r/m6.json
molsol/kde10_lstm_r/m7.h5
molsol/kde10_lstm_r/m7.json
molsol/kde10_lstm_r/m8.h5
molsol/kde10_lstm_r/m8.json
molsol/kde10_lstm_r/m9.h5
molsol/kde10_lstm_r/m9.json
molsol-0.0.3.dist-info/LICENSE
molsol-0.0.3.dist-info/METADATA
molsol-0.0.3.dist-info/WHEEL
molsol-0.0.3.dist-info/top_level.txt
molsol-0.0.3.dist-info/RECORD
